cp_manage/__init__.py
cp_manage/cli.py
cp_manage/utilities.py
pycpv-0.1.3.dist-info/METADATA
pycpv-0.1.3.dist-info/WHEEL
pycpv-0.1.3.dist-info/entry_points.txt
pycpv-0.1.3.dist-info/licenses/LICENSE
pycpv-0.1.3.dist-info/RECORD
